pytest_test_groups/__init__.py
pytest_test_groups-1.2.1.dist-info/licenses/LICENSE
pytest_test_groups-1.2.1.dist-info/METADATA
pytest_test_groups-1.2.1.dist-info/WHEEL
pytest_test_groups-1.2.1.dist-info/entry_points.txt
pytest_test_groups-1.2.1.dist-info/top_level.txt
pytest_test_groups-1.2.1.dist-info/RECORD
