Metadata-Version: 2.4
Name: pytest-test-groups
Version: 1.2.1
Summary: A Pytest plugin for running a subset of your tests by splitting them in to equally sized groups.
Author-email: Mark Adams <mark@markadams.me>
Maintainer-email: Mark Adams <mark@markadams.me>
License: The MIT License (MIT)
Project-URL: Documentation, https://github.com/mark-adams/pytest-test-groups
Project-URL: Repository, https://github.com/mark-adams/pytest-test-groups
Classifier: Development Status :: 5 - Production/Stable
Classifier: Intended Audience :: Developers
Classifier: License :: OSI Approved :: MIT License
Classifier: Operating System :: OS Independent
Classifier: Topic :: Software Development :: Testing
Classifier: Programming Language :: Python
Classifier: Programming Language :: Python :: 3
Classifier: Programming Language :: Python :: 3.8
Classifier: Programming Language :: Python :: 3.9
Classifier: Programming Language :: Python :: 3.10
Classifier: Programming Language :: Python :: 3.11
Classifier: Programming Language :: Python :: 3.12
Classifier: Programming Language :: Python :: 3.13
Requires-Python: >=3.8
License-File: LICENSE
Requires-Dist: pytest>=7.0.0
Dynamic: license-file
